{
	"name": "S2101_IP_DS",
	"properties": {
		"linkedServiceName": {
			"referenceName": "Cencus_Blob_Input_Ls",
			"type": "LinkedServiceReference"
		},
		"annotations": [],
		"type": "DelimitedText",
		"typeProperties": {
			"location": {
				"type": "AzureBlobStorageLocation",
				"fileName": "S2101_Combined_2017_lat.csv",
				"folderPath": "Files/S2101/Year/2019",
				"container": "data"
			},
			"columnDelimiter": ",",
			"escapeChar": "\\",
			"firstRowAsHeader": true,
			"quoteChar": "\""
		},
		"schema": []
	},
	"type": "Microsoft.DataFactory/factories/datasets"
}